pybind2csv/__init__.py
pybind2csv/__main__.py
pybind2csv/main.py
pybind2csv/parser.py
pybind2csv-0.1.2.dist-info/METADATA
pybind2csv-0.1.2.dist-info/WHEEL
pybind2csv-0.1.2.dist-info/entry_points.txt
pybind2csv-0.1.2.dist-info/top_level.txt
pybind2csv-0.1.2.dist-info/RECORD
