Metadata-Version: 2.4
Name: pybind2csv
Version: 0.1.2
Summary: A utility to parse DNS BIND zone and view files and convert them to CSV format.
Author-email: Your Name <your.email@example.com>
Project-URL: Homepage, https://github.com/fxyzbtc/pybind2csv
Project-URL: Repository, https://github.com/fxyzbtc/pybind2csv
Classifier: Programming Language :: Python :: 3
Classifier: Operating System :: OS Independent
Classifier: Topic :: Internet :: Name Service (DNS)
Classifier: Topic :: System :: Networking
Classifier: Topic :: Utilities
Requires-Python: >=3.12
Requires-Dist: dnspython>=2.7.0
Requires-Dist: loguru>=0.7.3
Requires-Dist: tqdm>=4.67.1
Requires-Dist: typer>=0.12.5
Provides-Extra: dev
Requires-Dist: pytest>=8.3.5; extra == "dev"
Requires-Dist: pytest-cov>=6.2.1; extra == "dev"
